ssfoodparser/__init__.py
ssfoodparser/parser.py
ssfoodparser-0.0.1.dist-info/LICENSE
ssfoodparser-0.0.1.dist-info/METADATA
ssfoodparser-0.0.1.dist-info/WHEEL
ssfoodparser-0.0.1.dist-info/top_level.txt
ssfoodparser-0.0.1.dist-info/RECORD
