Metadata-Version: 2.1
Name: ssfoodparser
Version: 0.0.1
Summary: A package for parsing food sheet from schoolsoft
Home-page: https://github.com/pluppen/schoolsoft-food-parser
Author: Elias Juremalm
Author-email: eliass.juremalm@gmail.com
License: UNKNOWN
Platform: UNKNOWN
Classifier: Programming Language :: Python :: 3
Classifier: License :: OSI Approved :: GNU General Public License v3 (GPLv3)
Classifier: Operating System :: OS Independent
Requires-Python: >=3.6
